tqdm_loggable/__init__.py
tqdm_loggable/auto.py
tqdm_loggable/manual_tests.py
tqdm_loggable/tqdm_logging.py
tqdm_loggable/utils.py
epoch8_tqdm_loggable-0.1.4.dist-info/METADATA
epoch8_tqdm_loggable-0.1.4.dist-info/WHEEL
epoch8_tqdm_loggable-0.1.4.dist-info/entry_points.txt
epoch8_tqdm_loggable-0.1.4.dist-info/RECORD
