Metadata-Version: 2.1
Name: epoch8-tqdm-loggable
Version: 0.1.4
Summary: TQDM progress bar friendliness for non-interactive terminals and logging output
Home-page: https://tradingstrategy.ai
License: MIT
Keywords: logging,tqdm,sentry,logstash,progress bar,datadog,new relic
Author: Mikko Ohtamaa
Author-email: mikko@opensourcehacker.com
Requires-Python: >=3.8,<4.0
Classifier: License :: OSI Approved :: MIT License
Classifier: Programming Language :: Python :: 3
Classifier: Programming Language :: Python :: 3.8
Classifier: Programming Language :: Python :: 3.9
Classifier: Programming Language :: Python :: 3.10
Classifier: Programming Language :: Python :: 3.11
Requires-Dist: tqdm (>=4.64.1,<5.0.0)
Project-URL: Repository, https://github.com/tradingstrategy-ai/tqdm-loggable
